Workbook

Sheet E.General
B2: Presupuesto para la ejecución del Proyecto de Gestión de Conocimiento – UCampus
B4: Ítem | C4: Valor en Pesos Colombianos ( $) | D4: Fuente de Financiamiento* | G4: Total ($)
D5: Fuente A | E5: Fuente B | F5: Recursos propios
B6: A. Personal
B7: =+'A-Personal'!B7 -> Estudiantes desarrolladores (Ing. de Sistemas y Computación): análisis, diseño, programación y documentación | C7: =+'A-Personal'!F7 -> 7000000 | D7: 0 | E7: 0 | F7: =+C7 -> 7000000 | G7: =+D7+E7+F7 -> 7000000
B8: Subtotal | C8: =+'A-Personal'!F11 -> 7000000 | D8: =SUM(D7:D7) -> 0 | E8: =SUM(E7:E7) -> 0 | F8: =SUM(F7:F7) -> 7000000 | G8: =SUM(G7:G7) -> 7000000
B9: B. Equipos y Software
B10: =+'B-Equipos'!B6 -> Computadores personales | C10: =+'B-Equipos'!F6 -> 6000000 | D10: 0 | E10: 0 | F10: =+C10 -> 6000000 | G10: =+D10+E10+F10 -> 6000000
B11: =+'B-Equipos'!B7 -> Software gratuito / educativo (Visual Studio Code, GitHub, Jira) | C11: =+'B-Equipos'!F7 -> 0 | D11: 0 | E11: 0 | F11: =+C11 -> 0 | G11: =+D11+E11+F11 -> 0
B13: Subtotal | C13: =+'B-Equipos'!F10 -> 6000000 | D13: =SUM(D10:D12) -> 0 | E13: =SUM(E10:E12) -> 0 | F13: =SUM(F10:F12) -> 6000000 | G13: =SUM(G10:G12) -> 6000000
B14: C. Viajes y Salidas de Campo
B15: =+'C-Viajes'!B6 -> Transporte a la universidad (entrevistas, reuniones y actividades del proyecto) | C15: =+'C-Viajes'!F6 -> 150000 | D15: 0 | E15: 0 | F15: =+C15 -> 150000 | G15: =+D15+E15+F15 -> 150000
B17: Subtotal | C17: =+'C-Viajes'!F9 -> 150000 | D17: =SUM(D15:D16) -> 0 | E17: =SUM(E15:E16) -> 0 | F17: =SUM(F15:F16) -> 150000 | G17: =SUM(G15:G16) -> 150000
B18: D. Materiales
B19: =+'D-Materiales'!B7 -> Conexión a Internet (2 estudiantes × 2 meses) | C19: =+'D-Materiales'!F7 -> 450000 | D19: 0 | E19: 0 | F19: =+C19 -> 450000 | G19: =+D19+E19+F19 -> 450000
B20: =+'D-Materiales'!B8 -> Bibliografía (artículos y documentos académicos de acceso abierto y recursos de la universidad) | C20: =+'D-Materiales'!F8 -> 0 | D20: 0 | E20: 0 | F20: =+C20 -> 0 | G20: =+D20+E20+F20 -> 0
B22: Subtotal | C22: =+'D-Materiales'!F11 -> 450000 | D22: =SUM(D19:D21) -> 0 | E22: =SUM(E19:E21) -> 0 | F22: =SUM(F19:F21) -> 450000 | G22: =SUM(G19:G21) -> 450000
B23: E. Asesorías técnicas y de soporte
B24: =+'E-Ase Tecn. y Soporte'!B7 -> No aplica | C24: =+'E-Ase Tecn. y Soporte'!F7 -> 0 | D24: 0 | E24: 0 | F24: =+C24 -> 0 | G24: =+D24+E24+F24 -> 0
B26: Subtotal | C26: =+'E-Ase Tecn. y Soporte'!F10 -> 0 | D26: =SUM(D24:D25) -> 0 | E26: =SUM(E24:E25) -> 0 | F26: =SUM(F24:F25) -> 0 | G26: =SUM(G24:G25) -> 0
B27: F. Otros
B28: =+'F-Otros'!B7 -> Montaje: computadores y servidores locales o servicios gratuitos para pruebas del prototipo | C28: =+'F-Otros'!F7 -> 0 | D28: 0 | E28: 0 | F28: =+C28 -> 0 | G28: =+D28+E28+F28 -> 0
B33: Subtotal | C33: =+'F-Otros'!F12 -> 0 | D33: =SUM(D28:D32) -> 0 | E33: =SUM(E28:E32) -> 0 | F33: =SUM(F28:F32) -> 0 | G33: =SUM(G28:G32) -> 0
B34: Total | C34: =+C8+C13+C17+C22+C26+C33 -> 13600000 | D34: =+D8+D13+D17+D22+D26+D33 -> 0 | E34: =+E8+E13+E17+E22+E26+E33 -> 0 | F34: =+F8+F13+F17+F22+F26+F33 -> 13600000 | G34: =+G8+G13+G17+G22+G26+G33 -> 13600000
B35: Porcentaje | C35: 1 | D35: =+D34/$C$34 -> 0 | E35: =+E34/$C$34 -> 0 | F35: =+F34/$C$34 -> 1 | G35: =+F35+E35+D35 -> 1
B36: *Rubros No Financiables con fuentes externas
B37: Nota: valores tomados de la sección 17 "Recursos necesarios" de la propuesta UCampus (total $13.600.000). Se asume financiación 100% con recursos propios de los estudiantes.

Sheet A-Personal
B3: Personal requerido para la ejecución del proyecto UCampus
B5: Categoría | C5: Salario - Honorario - Mensual ($) | D5: Cantidad | E5: Tiempo de Vinculación en meses | F5: Importe $
B7: Estudiantes desarrolladores (Ing. de Sistemas y Computación): análisis, diseño, programación y documentación | C7: 1750000 | D7: 2 | E7: 2 | F7: =+C7*D7*E7 -> 7000000
F8: =+C8*D8*E8 -> 0
F9: =+E9*D9*C9 -> 0
F10: =+E10*D10*C10 -> 0
B11: Subtotal | F11: =SUM(F7:F10) -> 7000000

Sheet B-Equipos
B2: Equipos y software
B4: Descripción | C4: Unidad de Medida | D4: Cantidad | E4: Precio Unitario ($) | F4: Importe $
B6: Computadores personales | C6: Unidad | D6: 2 | E6: 3000000 | F6: =+D6*E6 -> 6000000
B7: Software gratuito / educativo (Visual Studio Code, GitHub, Jira) | C7: Licencia | D7: 3 | E7: 0 | F7: =+D7*E7 -> 0
F8: =+D8*E8 -> 0
F9: =+D9*E9 -> 0
B10: Subtotal | F10: =SUM(F6:F9) -> 6000000

Sheet C-Viajes
B3: Viajes y salidas de Campo
B5: Concepto | C5: Tarifa diaria en $ | D5: Numero de días por viaje/salida de campo | E5: Número de Viajes y/o salidas de campo | F5: Importe ($)
B6: Transporte a la universidad (entrevistas, reuniones y actividades del proyecto) | C6: 15000 | D6: 1 | E6: 10 | F6: =+E6*D6*C6 -> 150000
F7: =+C7*E7 -> 0
F8: =+E8*D8*C8 -> 0
B9: Subtotal | F9: =SUM(F6:F8) -> 150000

Sheet D-Materiales
B3: Materiales
B5: Descripción del Material | C5: Unidad de medida | D5: Cantidad | E5: Precio Unitario ($) | F5: Importe $
B7: Conexión a Internet (2 estudiantes × 2 meses) | C7: Mes | D7: 4 | E7: 112500 | F7: =+E7*D7 -> 450000
B8: Bibliografía (artículos y documentos académicos de acceso abierto y recursos de la universidad) | C8: Global | D8: 1 | E8: 0 | F8: =+E8*D8 -> 0
F9: =+E9*D9 -> 0
F10: =+E10*D10 -> 0
B11: Subtotal | F11: =SUM(F7:F10) -> 450000

Sheet E-Ase Tecn. y Soporte
B3: Asesorías técnicas y soporte
B5: Descripción | C5: Unidad de medida | D5: Cantidad | E5: Precio Unitario ($) | F5: Importe $
B7: No aplica | C7: - | D7: 0 | E7: 0 | F7: =+E7*D7 -> 0
F8: =+E8*D8 -> 0
F9: =+E9*D9 -> 0
B10: Subtotal | F10: =SUM(F7:F9) -> 0

Sheet F-Otros
B3: Otros
B5: Descripción | C5: Unidad de medida | D5: Cantidad | E5: Precio Unitario ($) | F5: Importe $
B7: Montaje: computadores y servidores locales o servicios gratuitos para pruebas del prototipo | C7: Global | D7: 1 | E7: 0 | F7: =+E7*D7 -> 0
F8: =+E8*D8 -> 0
F9: =+E9*D9 -> 0
F10: =+E10*D10 -> 0
F11: =+E11*D11 -> 0
B12: Subtotal | F12: =SUM(F7:F11) -> 0

Sheet Fujo de Caja
B2: Flujo de Caja para la ejecución del proyecto UCampus – Componente egresos
B4: Actividades/Tareas/ subtareas** | E4: Fuentes de Financiamiento | H4: Requerimiento de recuros ($)
E5: Fuente A | F5: Fuente B | G5: Recursos propios | H5: Mes 1 (2 sep – 1 oct 2026) | I5: Mes 2 (2 oct – 3 nov 2026) | J5: Mes 3 | K5: Mes 4 | L5: Mes 5 | M5: Mes 6 | N5: Mes 7 | O5: Mes 8 | P5: Mes 9 | Q5: Mes 10 | R5: Mes n-1 | S5: Mes n | T5: Total
B6: Actividad 0. Alistamiento de recursos
C7: Equipos de cómputo y software (2 computadores; VS Code, GitHub, Jira) | E7: 0 | F7: 0 | G7: =+T7 -> 6000000 | H7: 6000000 | I7: 0 | T7: =SUM(H7:S7) -> 6000000
B8: Actividad 1. Análisis – Concebir (2 al 16 sep)
C9: 1.1 Recolección de información: elaborar, aplicar y analizar encuesta / entrevistas | E9: 0 | F9: 0 | G9: =+T9 -> 790000 | H9: 790000 | I9: 0 | T9: =SUM(H9:S9) -> 790000
C10: 1.2–1.6 Problema, objetivos, stakeholders, levantamiento y clasificación de requisitos | E10: 0 | F10: 0 | G10: =+T10 -> 1050000 | H10: 1050000 | I10: 0 | T10: =SUM(H10:S10) -> 1050000
B11: Actividad 2. Diseño – Diseñar (17 sep al 8 oct)
C12: 2.1–2.2 Arquitectura del sistema y diseño de base de datos (MER) | E12: 0 | F12: 0 | G12: =+T12 -> 900000 | H12: 900000 | I12: 0 | T12: =SUM(H12:S12) -> 900000
C13: 2.3–2.4 Diseño UML (casos de uso, clases) y diseño de interfaz | E13: 0 | F13: 0 | G13: =+T13 -> 1200000 | H13: 850000 | I13: 350000 | T13: =SUM(H13:S13) -> 1200000
B14: Actividad 3. Desarrollo – Implementar (9 al 16 oct)
C15: 3.1 Integración de los módulos | E15: 0 | F15: 0 | G15: =+T15 -> 1050000 | H15: 0 | I15: 1050000 | T15: =SUM(H15:S15) -> 1050000
C16: 3.2 Panel administrativo | E16: 0 | F16: 0 | G16: =+T16 -> 700000 | H16: 0 | I16: 700000 | T16: =SUM(H16:S16) -> 700000
B17: Actividad 4. Pruebas (19 al 26 oct)
C18: 4.1–4.3 Pruebas funcionales, pruebas de interfaz y corrección de errores | E18: 0 | F18: 0 | G18: =+T18 -> 830000 | H18: 0 | I18: 830000 | T18: =SUM(H18:S18) -> 830000
B19: Actividad 5. Despliegue – Operar (27 oct al 3 nov)
C20: 5.1 Puesta en funcionamiento y montaje en servidores locales o servicios gratuitos | E20: 0 | F20: 0 | G20: =+T20 -> 630000 | H20: 0 | I20: 630000 | T20: =SUM(H20:S20) -> 630000
B21: Actividad transversal. Conectividad
C22: Conexión a Internet (2 estudiantes) | E22: 0 | F22: 0 | G22: =+T22 -> 450000 | H22: 225000 | I22: 225000 | T22: =SUM(H22:S22) -> 450000
B23: Subtotales | E23: =SUM(E6:E22) -> 0 | F23: =SUM(F6:F22) -> 0 | G23: =SUM(G6:G22) -> 13600000 | H23: =SUM(H6:H22) -> 9815000 | I23: =SUM(I6:I22) -> 3785000 | T23: =SUM(T6:T22) -> 13600000
B24: Costo total del proyecto. | T24: =SUM(T6:T22) -> 13600000
B25: * Horizonte de ejecución del proyecto: 2 meses (2 de septiembre al 3 de noviembre de 2026), según el cronograma de la propuesta.

Sheet Hoja2
